{"id":"patroness_trustmebro","image":"https://bloodstar.clocktica.com/p/Elmar/trust-me-bro/patroness_trustmebro.png","reminders":["blessed"],"name":"Patroness","ability":"Each night, choose 1 alive player without outsider abilities (not yourself) who gets immune against wishes or changes caused by others until dusk. The Demon knows who.","attribution":"image: https://image.lexica.art/full_jpg/c6322780-960b-41d9-837f-20ea81c975a1","home_script":"trustmebro","type":"townsfolk","icon":"../../icons/patroness_trustmebro.png","affects_setup":false,"first_night":true,"other_nights":true}